README.md
setup.py
pypomelo/__init__.py
pypomelo/client.py
pypomelo/handler.py
pypomelo/message.py
pypomelo/protobuf.py
pypomelo/protocol.py
pypomelo/stream.py
pypomelo/tornadoclient.py
pypomelo.egg-info/PKG-INFO
pypomelo.egg-info/SOURCES.txt
pypomelo.egg-info/dependency_links.txt
pypomelo.egg-info/top_level.txt