Metadata-Version: 1.0
Name: pypomelo
Version: 1.0.0
Summary: PyPomelo is a pomelo protocol by python
Home-page: https://github.com/leenjewel/pypomelo
Author: leenjewel
Author-email: leenjewel@gmail.com
License: http://www.apache.org/licenses/LICENSE-2.0
Platform: UNKNOWN
